CHANGELOG.rst
LICENSE
MANIFEST.in
README.rst
setup.cfg
setup.py
src/kids/__init__.py
src/kids.data.egg-info/PKG-INFO
src/kids.data.egg-info/SOURCES.txt
src/kids.data.egg-info/dependency_links.txt
src/kids.data.egg-info/requires.txt
src/kids.data.egg-info/top_level.txt
src/kids/data/__init__.py
src/kids/data/dct.py
src/kids/data/dsp.py
src/kids/data/fmt.py
src/kids/data/format.py
src/kids/data/graph.py
src/kids/data/lib.py
src/kids/data/match.py
src/kids/data/mdict.py