Metadata-Version: 1.1
Name: kids.data
Version: 0.0.5
Summary: Kids data manipulation helpers.
Home-page: http://github.com/0k/kids.data
Author: Valentin Lab
Author-email: valentin.lab@kalysto.org
License: UNKNOWN
Platform: UNKNOWN
Classifier: Programming Language :: Python
Classifier: Topic :: Software Development :: Libraries :: Python Modules
Classifier: Development Status :: 3 - Alpha
Classifier: License :: OSI Approved :: BSD License
Classifier: Topic :: Software Development
Classifier: Intended Audience :: Developers
